odoo/addons/mrp_flattened_bom_xlsx_labour_cost/README.rst
odoo/addons/mrp_flattened_bom_xlsx_labour_cost/__init__.py
odoo/addons/mrp_flattened_bom_xlsx_labour_cost/__manifest__.py
odoo/addons/mrp_flattened_bom_xlsx_labour_cost/i18n/it.po
odoo/addons/mrp_flattened_bom_xlsx_labour_cost/i18n/mrp_flattened_bom_xlsx_labour_cost.pot
odoo/addons/mrp_flattened_bom_xlsx_labour_cost/models/__init__.py
odoo/addons/mrp_flattened_bom_xlsx_labour_cost/models/mrp_bom.py
odoo/addons/mrp_flattened_bom_xlsx_labour_cost/readme/CONTRIBUTORS.rst
odoo/addons/mrp_flattened_bom_xlsx_labour_cost/readme/DESCRIPTION.rst
odoo/addons/mrp_flattened_bom_xlsx_labour_cost/readme/USAGE.rst
odoo/addons/mrp_flattened_bom_xlsx_labour_cost/report/__init__.py
odoo/addons/mrp_flattened_bom_xlsx_labour_cost/report/flattened_bom_xlsx.py
odoo/addons/mrp_flattened_bom_xlsx_labour_cost/static/description/icon.png
odoo/addons/mrp_flattened_bom_xlsx_labour_cost/static/description/index.html
odoo_addon_mrp_flattened_bom_xlsx_labour_cost-16.0.1.0.0.2.dist-info/METADATA
odoo_addon_mrp_flattened_bom_xlsx_labour_cost-16.0.1.0.0.2.dist-info/WHEEL
odoo_addon_mrp_flattened_bom_xlsx_labour_cost-16.0.1.0.0.2.dist-info/top_level.txt
odoo_addon_mrp_flattened_bom_xlsx_labour_cost-16.0.1.0.0.2.dist-info/RECORD
