Metadata-Version: 2.1
Name: odoo-addon-mrp-flattened-bom-xlsx-labour-cost
Version: 16.0.1.0.0.2
Summary: Export Flattened BOM to Excel with labour cost
Home-page: https://github.com/OCA/manufacture-reporting
Author: ForgeFlow, Odoo Community Association (OCA)
Author-email: support@odoo-community.org
License: AGPL-3
Platform: UNKNOWN
Classifier: Programming Language :: Python
Classifier: Framework :: Odoo
Classifier: Framework :: Odoo :: 16.0
Classifier: License :: OSI Approved :: GNU Affero General Public License v3
Requires-Python: >=3.10
Requires-Dist: odoo-addon-mrp-flattened-bom-xlsx-direct-materials-cost <16.1dev,>=16.0dev
Requires-Dist: odoo <16.1dev,>=16.0a
